core_cortex-0.6.1.dist-info/licenses/LICENSE
cortex/__init__.py
cortex/auth.py
cortex/cortex.py
cortex/cortex_cursor.py
cortex/inference.py
cortex/metadata.py
cortex/routes_controller.py
cortex/schemas.py
cortex/wrappers.py
test/test_client.py
core_cortex-0.6.1.dist-info/METADATA
core_cortex-0.6.1.dist-info/WHEEL
core_cortex-0.6.1.dist-info/top_level.txt
core_cortex-0.6.1.dist-info/RECORD
