Metadata-Version: 2.4
Name: core-cortex
Version: 0.6.1
Summary: Python API client for Core Cortex
Author-email: CORE studio <ttcorestudio@gmail.com>
License: Copyright (c) 2020 CORE Studio | Thornton Tomasetti
Keywords: core,cortex,ai,ml,machine learning
Classifier: License :: OSI Approved :: MIT License
Classifier: Programming Language :: Python
Classifier: Programming Language :: Python :: 3
Requires-Python: >=3.9
License-File: LICENSE
Requires-Dist: requests
Requires-Dist: numpy
Requires-Dist: pandas
Requires-Dist: ipynbname
Requires-Dist: joblib
Requires-Dist: msal
Requires-Dist: msal-extensions
Dynamic: license-file
